{"ownerDBA":"DBA: UNITED ANCIENT ORDER OF DRUIDS 56","license":"17181","licenseType":"51","transfer":"","transferTo":false,"rawRecord":{"License Number":"17181","Status Changed From/To":"CANCEL ACTIVE","Type| Dup":"51 | 1","Original Issue Date":"01/21/1987","Expir. Date":"01/31/2024","Primary Owner and Premises Addr.":"DBA: UNITED ANCIENT ORDER OF DRUIDS 56                        UNITED ANCIENT ORDER OF DRUIDS                         501 SUMNER ST,                         BAKERSFIELD, CA  93305","Mailing Addr.":"4326 GREENWOOD ST                              NEWBURY PARK, CA  91320-5232","Transfer-From/To":"","Conditions":"","Escrow":"","District Code":"6","Geo Code":"1501","Prem Street":"501 SUMNER ST","City":"BAKERSFIELD","County":"15","Zip Code":"93305","Mailing Street":"4326 GREENWOOD ST","Mailing City":"NEWBURY PARK","Mailing Zip Code":"91320","Mailing State":"CA"},"mapsUrl":"https://maps.google.com?q=501%20SUMNER%20ST%2C%20BAKERSFIELD","licensePageUrl":"https://www.abc.ca.gov/licensing/license-lookup/single-license/?RPTTYPE=12&LICENSE=17181"}