{"ownerDBA":"DBA: NEW TUNG KEE NOODLE HOUSE","license":"583804","licenseType":"41","transfer":"","transferTo":false,"rawRecord":{"License Number":"583804","Status Changed From/To":"REVPEN ACTIVE","Type| Dup":"41 | 0","Original Issue Date":"09/28/2017","Expir. Date":"08/31/2024","Primary Owner and Premises Addr.":"DBA: NEW TUNG KEE NOODLE HOUSE                        BROKAW NOODLE INC                         1098 E BROKAW RD, STE 30,                         SAN JOSE, CA  95131-2309","Mailing Addr.":"","Transfer-From/To":"","Conditions":"","Escrow":"","District Code":"25","Geo Code":"4313","Prem Street":"1098 E BROKAW RD, STE 30","City":"SAN JOSE","County":"43","Zip Code":"95131","Mailing Street":"","Mailing City":"","Mailing Zip Code":"","Mailing State":""},"mapsUrl":"https://maps.google.com?q=1098%20E%20BROKAW%20RD%2C%20STE%2030%2C%20SAN%20JOSE","licensePageUrl":"https://www.abc.ca.gov/licensing/license-lookup/single-license/?RPTTYPE=12&LICENSE=583804"}