{"ownerDBA":"DBA: TAP THAT AXE","license":"651171","licenseType":"42","transfer":"","transferTo":false,"rawRecord":{"License Number":"651171","Status Changed From/To":"PEND ACTIVE","Type| Dup":"42 | 0","Original Issue Date":"12/05/2023","Expir. Date":"11/30/2024","Primary Owner and Premises Addr.":"DBA: TAP THAT AXE                         TAP THAT AXE LLC                         1509 N NORMA ST,                         RIDGECREST, CA  93555-2570","Mailing Addr.":"1206 N LAS POSAS CT                              RIDGECREST, CA  93555-2310","Transfer-From/To":"","Conditions":"7","Escrow":"","District Code":"6","Geo Code":"1510","Prem Street":"1509 N NORMA ST","City":"RIDGECREST","County":"15","Zip Code":"93555","Mailing Street":"1206 N LAS POSAS CT","Mailing City":"RIDGECREST","Mailing Zip Code":"93555","Mailing State":"CA"},"mapsUrl":"https://maps.google.com?q=1509%20N%20NORMA%20ST%2C%20RIDGECREST","licensePageUrl":"https://www.abc.ca.gov/licensing/license-lookup/single-license/?RPTTYPE=12&LICENSE=651171"}