{"ownerDBA":"DBA: MISSION BAY WINE & CHEESE","license":"653279","licenseType":"47","transfer":"47-583687","transferTo":false,"rawRecord":{"License Number":"653279","Status Changed From/To":"PEND ACTIVE","Type| Dup":"47 | 0","Original Issue Date":"11/21/2023","Expir. Date":"10/31/2024","Primary Owner and Premises Addr.":"DBA: MISSION BAY WINE & CHEESE                        MISSION BAY WINE & CHEESE, LLC                         640 & 650 TERRY FRANCOIS BLVD,                         SAN FRANCISCO, CA  94158-2204","Mailing Addr.":"3001 BRIDGEWAY, K-325                              SAUSALITO, CA  94965","Transfer-From/To":"47-583687","Conditions":"7","Escrow":"CALIFORNIA BUSINESS ESCROW 1748 MAIN ST ESCALON, CA  95320-1927","District Code":"24","Geo Code":"3800","Prem Street":"640 & 650 TERRY FRANCOIS BLVD","City":"SAN FRANCISCO","County":"38","Zip Code":"94158","Mailing Street":"3001 BRIDGEWAY, K-325","Mailing City":"SAUSALITO","Mailing Zip Code":"94965","Mailing State":"CA"},"mapsUrl":"https://maps.google.com?q=640%20%26%20650%20TERRY%20FRANCOIS%20BLVD%2C%20SAN%20FRANCISCO","licensePageUrl":"https://www.abc.ca.gov/licensing/license-lookup/single-license/?RPTTYPE=12&LICENSE=653279"}