{"ownerDBA":"DBA: AMERICAN SOCIAL","license":"652663","licenseType":"47","transfer":"47-574191","transferTo":false,"rawRecord":{"License Number":"652663","Status Changed From/To":"PEND ACTIVE","Type| Dup":"47 | 0","Original Issue Date":"11/27/2023","Expir. Date":"10/31/2024","Primary Owner and Premises Addr.":"DBA: AMERICAN SOCIAL                        FIRST STREET HILMAR LLC                         122 W RIVER RD,                         RIPON, CA  95366","Mailing Addr.":"2370 W MONTE VISTA AVE                              TURLOCK, CA  95382-9668","Transfer-From/To":"47-574191","Conditions":"","Escrow":"MICHAEL S WARDA 2350 W MONTE VISTA AVE TURLOCK, CA  95382","District Code":"29","Geo Code":"3904","Prem Street":"122 W RIVER RD","City":"RIPON","County":"39","Zip Code":"95366","Mailing Street":"2370 W MONTE VISTA AVE","Mailing City":"TURLOCK","Mailing Zip Code":"95382","Mailing State":"CA"},"mapsUrl":"https://maps.google.com?q=122%20W%20RIVER%20RD%2C%20RIPON","licensePageUrl":"https://www.abc.ca.gov/licensing/license-lookup/single-license/?RPTTYPE=12&LICENSE=652663"}