{"ownerDBA":"DBA: WILLOW GLEN SALOON","license":"649357","licenseType":"47","transfer":"47-234161","transferTo":false,"rawRecord":{"License Number":"649357","Status Changed From/To":"PEND ACTIVE","Type| Dup":"47 | 0","Original Issue Date":"12/04/2023","Expir. Date":"11/30/2024","Primary Owner and Premises Addr.":"DBA: WILLOW GLEN SALOON                        WILLOW GLEN SALOON, LLC                         13809 WILLOW GLEN RD,                         OREGON HOUSE, CA  95962","Mailing Addr.":"PO BOX 1835                              MOUNTAIN VIEW, CA  94042","Transfer-From/To":"47-234161","Conditions":"7","Escrow":"","District Code":"23","Geo Code":"5800","Prem Street":"13809 WILLOW GLEN RD","City":"OREGON HOUSE","County":"58","Zip Code":"95962","Mailing Street":"PO BOX 1835","Mailing City":"MOUNTAIN VIEW","Mailing Zip Code":"94042","Mailing State":"CA"},"mapsUrl":"https://maps.google.com?q=13809%20WILLOW%20GLEN%20RD%2C%20OREGON%20HOUSE","licensePageUrl":"https://www.abc.ca.gov/licensing/license-lookup/single-license/?RPTTYPE=12&LICENSE=649357"}