{"ownerDBA":"DBA: RESIDENCCE INN BEVERLY HILLS","license":"651133","licenseType":"58","transfer":"47-301117","transferTo":false,"rawRecord":{"License Number":"651133","Status Changed From/To":"PEND ACTIVE","Type| Dup":"58 | 1","Original Issue Date":"01/23/2024","Expir. Date":"12/31/2024","Primary Owner and Premises Addr.":"DBA: RESIDENCCE INN BEVERLY HILLS                        SEAVIEW INVESTORS, LLC                         1177 S BEVERLY DR,                         LOS ANGELES, CA  90035-1119","Mailing Addr.":"3334 E COAST HWY, STE 410                              CORONA DEL MAR, CA  92625-2328","Transfer-From/To":"47-301117","Conditions":"7","Escrow":"CALIFORNIA BUSINESS ESCROW INC 1748 MAIN ST ESCALON, CA  95320-1927","District Code":"4","Geo Code":"1933","Prem Street":"1177 S BEVERLY DR","City":"LOS ANGELES","County":"19","Zip Code":"90035","Mailing Street":"3334 E COAST HWY, STE 410","Mailing City":"CORONA DEL MAR","Mailing Zip Code":"92625","Mailing State":"CA"},"mapsUrl":"https://maps.google.com?q=1177%20S%20BEVERLY%20DR%2C%20LOS%20ANGELES","licensePageUrl":"https://www.abc.ca.gov/licensing/license-lookup/single-license/?RPTTYPE=12&LICENSE=651133"}